LICENCE.txt
sumo_simple.py
sumologic_simple-0.1.1.dist-info/WHEEL
sumologic_simple-0.1.1.dist-info/METADATA
sumologic_simple-0.1.1.dist-info/RECORD
